lazyql/__init__.py
lazyql/audit.py
lazyql/exceptions.py
lazyql/factory/__init__.py
lazyql/factory/crud_factory.py
lazyql/factory/input_type_builder.py
lazyql/factory/mutation_builder.py
lazyql/factory/output_type_builder.py
lazyql/factory/patch_input_helper.py
lazyql/factory/query_builder.py
lazyql/factory/sub_model.py
lazyql/factory/sub_model_registry.py
lazyql/factory/type_builder.py
lazyql/filters/__init__.py
lazyql/filters/builder.py
lazyql/filters/operators.py
lazyql/filters/parser.py
lazyql/filters/registry.py
lazyql/filters/type_generator.py
lazyql/indexes.py
lazyql/models.py
lazyql/permissions/__init__.py
lazyql/permissions/permission_helpers.py
lazyql/permissions/permissions.py
lazyql/protocol.py
lazyql/service.py
lazyql/utils.py
lazyql-0.1.15.dist-info/LICENSE
lazyql-0.1.15.dist-info/METADATA
lazyql-0.1.15.dist-info/WHEEL
lazyql-0.1.15.dist-info/RECORD
