Metadata-Version: 2.1
Name: LazyQL
Version: 0.1.15
Summary: A FastAPI and Strawberry GraphQL library to create CRUD APIs over MongoDB with advanced filtering capabilities.
Home-page: https://gitlab.com/creibaud/lazyql
License: MIT
Keywords: graphql,mongodb,crud,fastapi,strawberry
Author: creibaud
Requires-Python: >=3.11,<4.0
Classifier: License :: OSI Approved :: MIT License
Classifier: Programming Language :: Python :: 3
Classifier: Programming Language :: Python :: 3.11
Classifier: Programming Language :: Python :: 3.12
Requires-Dist: deepdiff (>=8.6.1,<9.0.0)
Requires-Dist: motor (>=3.7.1,<4.0.0)
Requires-Dist: pydantic (>=2.12.5,<3.0.0)
Requires-Dist: strawberry-graphql[fastapi] (>=0.287.2,<0.288.0)
Project-URL: Documentation, https://gitlab.com/creibaud/lazyql/-/blob/main/README.md
Project-URL: Repository, https://gitlab.com/creibaud/lazyql
